[
  {
    "name": "Warung Kopi",
    "superclasses": "",
    "subclasses": "",
    "type": 1,
    "responsibilities": [
      "fasilitas",
      "kopi",
      "kasir",
      "pelayan",
      "makanan"
    ],
    "collaborators": [
      "harga",
      "pembeli",
      "tempat"
    ]
  },
  {
    "name": "Harga",
    "superclasses": "",
    "subclasses": "",
    "type": 1,
    "responsibilities": [
      "memasak",
      "menyediakan ",
      "membeli"
    ],
    "collaborators": [
      "Warung kopi",
      "Pembeli"
    ]
  },
  {
    "name": "Pembeli",
    "superclasses": "",
    "subclasses": "",
    "type": 1,
    "responsibilities": [
      "cowok",
      "cewek",
      "mahasiswa",
      "pecinta kopi"
    ],
    "collaborators": [
      "harga",
      "warung kopi",
      "tempat"
    ]
  },
  {
    "name": "tempat",
    "superclasses": "",
    "subclasses": "",
    "type": 1,
    "responsibilities": [
      "alamat"
    ],
    "collaborators": [
      "warung kopi"
    ]
  }
]
